{
  "match_id": "733985",
  "date": "2014-05-07",
  "venue": "Feroz Shah Kotla",
  "teams": {
    "team1": "Delhi Daredevils",
    "team2": "Kolkata Knight Riders"
  },
  "result": {
    "winner": "Kolkata Knight Riders",
    "margin": "8 wickets",
    "margin_type": "wickets"
  },
  "innings": [
    {
      "innings_number": 1,
      "batting_team": "Delhi Daredevils",
      "bowling_team": "Kolkata Knight Riders",
      "final_score": 160,
      "wickets": 5,
      "overs": 20.0,
      "win_probability_curve": [
        {
          "over": 0,
          "ball": 0,
          "probability": 0.478
        },
        {
          "over": 0,
          "ball": 1,
          "probability": 0.476
        },
        {
          "over": 0,
          "ball": 2,
          "probability": 0.486
        },
        {
          "over": 0,
          "ball": 3,
          "probability": 0.484
        },
        {
          "over": 0,
          "ball": 4,
          "probability": 0.48
        },
        {
          "over": 0,
          "ball": 5,
          "probability": 0.487
        },
        {
          "over": 1,
          "ball": 0,
          "probability": 0.488
        },
        {
          "over": 1,
          "ball": 1,
          "probability": 0.482
        },
        {
          "over": 1,
          "ball": 2,
          "probability": 0.483
        },
        {
          "over": 1,
          "ball": 3,
          "probability": 0.504
        },
        {
          "over": 1,
          "ball": 4,
          "probability": 0.498
        },
        {
          "over": 1,
          "ball": 5,
          "probability": 0.492
        },
        {
          "over": 2,
          "ball": 0,
          "probability": 0.493
        },
        {
          "over": 2,
          "ball": 1,
          "probability": 0.487
        },
        {
          "over": 2,
          "ball": 2,
          "probability": 0.48
        },
        {
          "over": 2,
          "ball": 3,
          "probability": 0.401
        },
        {
          "over": 2,
          "ball": 4,
          "probability": 0.395
        },
        {
          "over": 2,
          "ball": 5,
          "probability": 0.416
        },
        {
          "over": 3,
          "ball": 0,
          "probability": 0.409
        },
        {
          "over": 3,
          "ball": 1,
          "probability": 0.403
        },
        {
          "over": 3,
          "ball": 2,
          "probability": 0.397
        },
        {
          "over": 3,
          "ball": 3,
          "probability": 0.391
        },
        {
          "over": 3,
          "ball": 4,
          "probability": 0.391
        },
        {
          "over": 3,
          "ball": 5,
          "probability": 0.385
        },
        {
          "over": 4,
          "ball": 0,
          "probability": 0.385
        },
        {
          "over": 4,
          "ball": 1,
          "probability": 0.386
        },
        {
          "over": 4,
          "ball": 2,
          "probability": 0.38
        },
        {
          "over": 4,
          "ball": 3,
          "probability": 0.401
        },
        {
          "over": 4,
          "ball": 4,
          "probability": 0.395
        },
        {
          "over": 4,
          "ball": 5,
          "probability": 0.388
        },
        {
          "over": 5,
          "ball": 0,
          "probability": 0.389
        },
        {
          "over": 5,
          "ball": 1,
          "probability": 0.383
        },
        {
          "over": 5,
          "ball": 2,
          "probability": 0.376
        },
        {
          "over": 5,
          "ball": 3,
          "probability": 0.304
        },
        {
          "over": 5,
          "ball": 4,
          "probability": 0.304
        },
        {
          "over": 5,
          "ball": 5,
          "probability": 0.305
        },
        {
          "over": 6,
          "ball": 0,
          "probability": 0.305
        },
        {
          "over": 6,
          "ball": 1,
          "probability": 0.306
        },
        {
          "over": 6,
          "ball": 2,
          "probability": 0.306
        },
        {
          "over": 6,
          "ball": 3,
          "probability": 0.312
        },
        {
          "over": 6,
          "ball": 4,
          "probability": 0.307
        },
        {
          "over": 6,
          "ball": 5,
          "probability": 0.313
        },
        {
          "over": 6,
          "ball": 6,
          "probability": 0.333
        },
        {
          "over": 7,
          "ball": 0,
          "probability": 0.334
        },
        {
          "over": 7,
          "ball": 1,
          "probability": 0.334
        },
        {
          "over": 7,
          "ball": 2,
          "probability": 0.368
        },
        {
          "over": 7,
          "ball": 3,
          "probability": 0.369
        },
        {
          "over": 7,
          "ball": 4,
          "probability": 0.369
        },
        {
          "over": 7,
          "ball": 5,
          "probability": 0.37
        },
        {
          "over": 8,
          "ball": 0,
          "probability": 0.391
        },
        {
          "over": 8,
          "ball": 1,
          "probability": 0.392
        },
        {
          "over": 8,
          "ball": 2,
          "probability": 0.385
        },
        {
          "over": 8,
          "ball": 3,
          "probability": 0.393
        },
        {
          "over": 8,
          "ball": 4,
          "probability": 0.394
        },
        {
          "over": 8,
          "ball": 5,
          "probability": 0.415
        },
        {
          "over": 9,
          "ball": 0,
          "probability": 0.339
        },
        {
          "over": 9,
          "ball": 1,
          "probability": 0.34
        },
        {
          "over": 9,
          "ball": 2,
          "probability": 0.34
        },
        {
          "over": 9,
          "ball": 3,
          "probability": 0.341
        },
        {
          "over": 9,
          "ball": 4,
          "probability": 0.335
        },
        {
          "over": 9,
          "ball": 5,
          "probability": 0.335
        },
        {
          "over": 10,
          "ball": 0,
          "probability": 0.336
        },
        {
          "over": 10,
          "ball": 1,
          "probability": 0.37
        },
        {
          "over": 10,
          "ball": 2,
          "probability": 0.364
        },
        {
          "over": 10,
          "ball": 3,
          "probability": 0.365
        },
        {
          "over": 10,
          "ball": 4,
          "probability": 0.365
        },
        {
          "over": 10,
          "ball": 5,
          "probability": 0.386
        },
        {
          "over": 11,
          "ball": 0,
          "probability": 0.408
        },
        {
          "over": 11,
          "ball": 1,
          "probability": 0.402
        },
        {
          "over": 11,
          "ball": 2,
          "probability": 0.409
        },
        {
          "over": 11,
          "ball": 3,
          "probability": 0.403
        },
        {
          "over": 11,
          "ball": 4,
          "probability": 0.404
        },
        {
          "over": 11,
          "ball": 5,
          "probability": 0.328
        },
        {
          "over": 12,
          "ball": 0,
          "probability": 0.322
        },
        {
          "over": 12,
          "ball": 1,
          "probability": 0.323
        },
        {
          "over": 12,
          "ball": 2,
          "probability": 0.324
        },
        {
          "over": 12,
          "ball": 3,
          "probability": 0.324
        },
        {
          "over": 12,
          "ball": 4,
          "probability": 0.331
        },
        {
          "over": 12,
          "ball": 5,
          "probability": 0.325
        },
        {
          "over": 12,
          "ball": 6,
          "probability": 0.325
        },
        {
          "over": 13,
          "ball": 0,
          "probability": 0.346
        },
        {
          "over": 13,
          "ball": 1,
          "probability": 0.353
        },
        {
          "over": 13,
          "ball": 2,
          "probability": 0.353
        },
        {
          "over": 13,
          "ball": 3,
          "probability": 0.347
        },
        {
          "over": 13,
          "ball": 4,
          "probability": 0.341
        },
        {
          "over": 13,
          "ball": 5,
          "probability": 0.342
        },
        {
          "over": 14,
          "ball": 0,
          "probability": 0.342
        },
        {
          "over": 14,
          "ball": 1,
          "probability": 0.343
        },
        {
          "over": 14,
          "ball": 2,
          "probability": 0.337
        },
        {
          "over": 14,
          "ball": 3,
          "probability": 0.338
        },
        {
          "over": 14,
          "ball": 4,
          "probability": 0.338
        },
        {
          "over": 14,
          "ball": 5,
          "probability": 0.332
        },
        {
          "over": 15,
          "ball": 0,
          "probability": 0.333
        },
        {
          "over": 15,
          "ball": 1,
          "probability": 0.327
        },
        {
          "over": 15,
          "ball": 2,
          "probability": 0.321
        },
        {
          "over": 15,
          "ball": 3,
          "probability": 0.321
        },
        {
          "over": 15,
          "ball": 4,
          "probability": 0.322
        },
        {
          "over": 15,
          "ball": 5,
          "probability": 0.255
        },
        {
          "over": 16,
          "ball": 0,
          "probability": 0.256
        },
        {
          "over": 16,
          "ball": 1,
          "probability": 0.274
        },
        {
          "over": 16,
          "ball": 2,
          "probability": 0.268
        },
        {
          "over": 16,
          "ball": 3,
          "probability": 0.299
        },
        {
          "over": 16,
          "ball": 4,
          "probability": 0.299
        },
        {
          "over": 16,
          "ball": 5,
          "probability": 0.3
        },
        {
          "over": 17,
          "ball": 0,
          "probability": 0.3
        },
        {
          "over": 17,
          "ball": 1,
          "probability": 0.301
        },
        {
          "over": 17,
          "ball": 2,
          "probability": 0.333
        },
        {
          "over": 17,
          "ball": 3,
          "probability": 0.334
        },
        {
          "over": 17,
          "ball": 4,
          "probability": 0.355
        },
        {
          "over": 17,
          "ball": 5,
          "probability": 0.376
        },
        {
          "over": 18,
          "ball": 0,
          "probability": 0.376
        },
        {
          "over": 18,
          "ball": 1,
          "probability": 0.377
        },
        {
          "over": 18,
          "ball": 2,
          "probability": 0.413
        },
        {
          "over": 18,
          "ball": 3,
          "probability": 0.406
        },
        {
          "over": 18,
          "ball": 4,
          "probability": 0.407
        },
        {
          "over": 18,
          "ball": 5,
          "probability": 0.429
        },
        {
          "over": 19,
          "ball": 0,
          "probability": 0.423
        },
        {
          "over": 19,
          "ball": 1,
          "probability": 0.423
        },
        {
          "over": 19,
          "ball": 2,
          "probability": 0.424
        },
        {
          "over": 19,
          "ball": 3,
          "probability": 0.432
        },
        {
          "over": 19,
          "ball": 4,
          "probability": 0.432
        },
        {
          "over": 19,
          "ball": 5,
          "probability": 0.433
        }
      ],
      "key_moments": [
        {
          "over": 2,
          "ball": 2,
          "swing": 0.08,
          "probability_before": 0.48,
          "probability_after": 0.401,
          "description": "Wicket"
        },
        {
          "over": 8,
          "ball": 5,
          "swing": 0.076,
          "probability_before": 0.415,
          "probability_after": 0.339,
          "description": "Wicket"
        },
        {
          "over": 11,
          "ball": 4,
          "swing": 0.075,
          "probability_before": 0.404,
          "probability_after": 0.328,
          "description": "Wicket"
        },
        {
          "over": 5,
          "ball": 2,
          "swing": 0.073,
          "probability_before": 0.376,
          "probability_after": 0.304,
          "description": "Wicket"
        },
        {
          "over": 15,
          "ball": 4,
          "swing": 0.067,
          "probability_before": 0.322,
          "probability_after": 0.255,
          "description": "Wicket"
        }
      ],
      "phases": {
        "powerplay": {
          "overs": "1-6",
          "runs": 29,
          "wickets": 2,
          "run_rate": 4.83,
          "required_run_rate": null
        },
        "middle": {
          "overs": "7-15",
          "runs": 74,
          "wickets": 2,
          "run_rate": 8.22,
          "required_run_rate": null
        },
        "death": {
          "overs": "16-20",
          "runs": 57,
          "wickets": 1,
          "run_rate": 11.4,
          "required_run_rate": null
        }
      },
      "pressure_index": 0.746,
      "match_shape": null
    },
    {
      "innings_number": 2,
      "batting_team": "Kolkata Knight Riders",
      "bowling_team": "Delhi Daredevils",
      "final_score": 161,
      "wickets": 2,
      "overs": 18.33,
      "win_probability_curve": [
        {
          "over": 0,
          "ball": 0,
          "probability": 0.563
        },
        {
          "over": 0,
          "ball": 1,
          "probability": 0.55
        },
        {
          "over": 0,
          "ball": 2,
          "probability": 0.548
        },
        {
          "over": 0,
          "ball": 3,
          "probability": 0.536
        },
        {
          "over": 0,
          "ball": 4,
          "probability": 0.523
        },
        {
          "over": 0,
          "ball": 5,
          "probability": 0.523
        },
        {
          "over": 1,
          "ball": 0,
          "probability": 0.51
        },
        {
          "over": 1,
          "ball": 1,
          "probability": 0.497
        },
        {
          "over": 1,
          "ball": 2,
          "probability": 0.538
        },
        {
          "over": 1,
          "ball": 3,
          "probability": 0.539
        },
        {
          "over": 1,
          "ball": 4,
          "probability": 0.526
        },
        {
          "over": 1,
          "ball": 5,
          "probability": 0.569
        },
        {
          "over": 2,
          "ball": 0,
          "probability": 0.611
        },
        {
          "over": 2,
          "ball": 1,
          "probability": 0.612
        },
        {
          "over": 2,
          "ball": 2,
          "probability": 0.654
        },
        {
          "over": 2,
          "ball": 3,
          "probability": 0.693
        },
        {
          "over": 2,
          "ball": 4,
          "probability": 0.694
        },
        {
          "over": 2,
          "ball": 5,
          "probability": 0.696
        },
        {
          "over": 3,
          "ball": 0,
          "probability": 0.697
        },
        {
          "over": 3,
          "ball": 1,
          "probability": 0.698
        },
        {
          "over": 3,
          "ball": 2,
          "probability": 0.699
        },
        {
          "over": 3,
          "ball": 3,
          "probability": 0.687
        },
        {
          "over": 3,
          "ball": 4,
          "probability": 0.675
        },
        {
          "over": 3,
          "ball": 5,
          "probability": 0.676
        },
        {
          "over": 4,
          "ball": 0,
          "probability": 0.663
        },
        {
          "over": 4,
          "ball": 1,
          "probability": 0.677
        },
        {
          "over": 4,
          "ball": 2,
          "probability": 0.677
        },
        {
          "over": 4,
          "ball": 3,
          "probability": 0.678
        },
        {
          "over": 4,
          "ball": 4,
          "probability": 0.665
        },
        {
          "over": 4,
          "ball": 5,
          "probability": 0.666
        },
        {
          "over": 4,
          "ball": 6,
          "probability": 0.68
        },
        {
          "over": 5,
          "ball": 0,
          "probability": 0.744
        },
        {
          "over": 5,
          "ball": 1,
          "probability": 0.757
        },
        {
          "over": 5,
          "ball": 2,
          "probability": 0.758
        },
        {
          "over": 5,
          "ball": 3,
          "probability": 0.791
        },
        {
          "over": 5,
          "ball": 4,
          "probability": 0.802
        },
        {
          "over": 5,
          "ball": 5,
          "probability": 0.793
        },
        {
          "over": 6,
          "ball": 0,
          "probability": 0.793
        },
        {
          "over": 6,
          "ball": 1,
          "probability": 0.794
        },
        {
          "over": 6,
          "ball": 2,
          "probability": 0.795
        },
        {
          "over": 6,
          "ball": 3,
          "probability": 0.795
        },
        {
          "over": 6,
          "ball": 4,
          "probability": 0.796
        },
        {
          "over": 6,
          "ball": 5,
          "probability": 0.796
        },
        {
          "over": 7,
          "ball": 0,
          "probability": 0.845
        },
        {
          "over": 7,
          "ball": 1,
          "probability": 0.87
        },
        {
          "over": 7,
          "ball": 2,
          "probability": 0.863
        },
        {
          "over": 7,
          "ball": 3,
          "probability": 0.864
        },
        {
          "over": 7,
          "ball": 4,
          "probability": 0.864
        },
        {
          "over": 7,
          "ball": 5,
          "probability": 0.873
        },
        {
          "over": 8,
          "ball": 0,
          "probability": 0.873
        },
        {
          "over": 8,
          "ball": 1,
          "probability": 0.866
        },
        {
          "over": 8,
          "ball": 2,
          "probability": 0.866
        },
        {
          "over": 8,
          "ball": 3,
          "probability": 0.867
        },
        {
          "over": 8,
          "ball": 4,
          "probability": 0.867
        },
        {
          "over": 8,
          "ball": 5,
          "probability": 0.867
        },
        {
          "over": 9,
          "ball": 0,
          "probability": 0.868
        },
        {
          "over": 9,
          "ball": 1,
          "probability": 0.891
        },
        {
          "over": 9,
          "ball": 2,
          "probability": 0.891
        },
        {
          "over": 9,
          "ball": 3,
          "probability": 0.898
        },
        {
          "over": 9,
          "ball": 4,
          "probability": 0.899
        },
        {
          "over": 9,
          "ball": 5,
          "probability": 0.918
        },
        {
          "over": 10,
          "ball": 0,
          "probability": 0.918
        },
        {
          "over": 10,
          "ball": 1,
          "probability": 0.918
        },
        {
          "over": 10,
          "ball": 2,
          "probability": 0.919
        },
        {
          "over": 10,
          "ball": 3,
          "probability": 0.919
        },
        {
          "over": 10,
          "ball": 4,
          "probability": 0.935
        },
        {
          "over": 10,
          "ball": 5,
          "probability": 0.948
        },
        {
          "over": 11,
          "ball": 0,
          "probability": 0.949
        },
        {
          "over": 11,
          "ball": 1,
          "probability": 0.945
        },
        {
          "over": 11,
          "ball": 2,
          "probability": 0.945
        },
        {
          "over": 11,
          "ball": 3,
          "probability": 0.95
        },
        {
          "over": 11,
          "ball": 4,
          "probability": 0.95
        },
        {
          "over": 11,
          "ball": 5,
          "probability": 0.929
        },
        {
          "over": 12,
          "ball": 0,
          "probability": 0.929
        },
        {
          "over": 12,
          "ball": 1,
          "probability": 0.93
        },
        {
          "over": 12,
          "ball": 2,
          "probability": 0.936
        },
        {
          "over": 12,
          "ball": 3,
          "probability": 0.936
        },
        {
          "over": 12,
          "ball": 4,
          "probability": 0.946
        },
        {
          "over": 12,
          "ball": 5,
          "probability": 0.947
        },
        {
          "over": 13,
          "ball": 0,
          "probability": 0.947
        },
        {
          "over": 13,
          "ball": 1,
          "probability": 0.96
        },
        {
          "over": 13,
          "ball": 2,
          "probability": 0.96
        },
        {
          "over": 13,
          "ball": 3,
          "probability": 0.961
        },
        {
          "over": 13,
          "ball": 4,
          "probability": 0.961
        },
        {
          "over": 13,
          "ball": 5,
          "probability": 0.961
        },
        {
          "over": 14,
          "ball": 0,
          "probability": 0.958
        },
        {
          "over": 14,
          "ball": 1,
          "probability": 0.954
        },
        {
          "over": 14,
          "ball": 2,
          "probability": 0.954
        },
        {
          "over": 14,
          "ball": 3,
          "probability": 0.955
        },
        {
          "over": 14,
          "ball": 4,
          "probability": 0.95
        },
        {
          "over": 14,
          "ball": 5,
          "probability": 0.945
        },
        {
          "over": 15,
          "ball": 0,
          "probability": 0.951
        },
        {
          "over": 15,
          "ball": 1,
          "probability": 0.956
        },
        {
          "over": 15,
          "ball": 2,
          "probability": 0.961
        },
        {
          "over": 15,
          "ball": 3,
          "probability": 0.961
        },
        {
          "over": 15,
          "ball": 4,
          "probability": 0.957
        },
        {
          "over": 15,
          "ball": 5,
          "probability": 0.97
        },
        {
          "over": 16,
          "ball": 0,
          "probability": 0.971
        },
        {
          "over": 16,
          "ball": 1,
          "probability": 0.971
        },
        {
          "over": 16,
          "ball": 2,
          "probability": 0.981
        },
        {
          "over": 16,
          "ball": 3,
          "probability": 0.982
        },
        {
          "over": 16,
          "ball": 4,
          "probability": 0.979
        },
        {
          "over": 16,
          "ball": 5,
          "probability": 0.991
        },
        {
          "over": 17,
          "ball": 0,
          "probability": 0.991
        },
        {
          "over": 17,
          "ball": 1,
          "probability": 0.99
        },
        {
          "over": 17,
          "ball": 2,
          "probability": 0.986
        },
        {
          "over": 17,
          "ball": 3,
          "probability": 0.984
        },
        {
          "over": 17,
          "ball": 4,
          "probability": 0.982
        },
        {
          "over": 17,
          "ball": 5,
          "probability": 0.991
        },
        {
          "over": 18,
          "ball": 0,
          "probability": 0.992
        },
        {
          "over": 18,
          "ball": 1,
          "probability": 0.996
        }
      ],
      "key_moments": [
        {
          "over": 4,
          "ball": 6,
          "swing": 0.064,
          "probability_before": 0.68,
          "probability_after": 0.744,
          "description": "Boundary"
        },
        {
          "over": 6,
          "ball": 5,
          "swing": 0.049,
          "probability_before": 0.796,
          "probability_after": 0.845,
          "description": "Boundary"
        },
        {
          "over": 1,
          "ball": 4,
          "swing": 0.043,
          "probability_before": 0.526,
          "probability_after": 0.569,
          "description": "Boundary"
        },
        {
          "over": 1,
          "ball": 5,
          "swing": 0.042,
          "probability_before": 0.569,
          "probability_after": 0.611,
          "description": "Boundary"
        },
        {
          "over": 1,
          "ball": 1,
          "swing": 0.042,
          "probability_before": 0.497,
          "probability_after": 0.538,
          "description": "Boundary"
        }
      ],
      "phases": {
        "powerplay": {
          "overs": "1-6",
          "runs": 52,
          "wickets": 0,
          "run_rate": 8.67,
          "required_run_rate": 8.08
        },
        "middle": {
          "overs": "7-15",
          "runs": 76,
          "wickets": 1,
          "run_rate": 8.44,
          "required_run_rate": 6.99
        },
        "death": {
          "overs": "16-20",
          "runs": 33,
          "wickets": 1,
          "run_rate": 6.6,
          "required_run_rate": 4.61
        }
      },
      "pressure_index": 0.338,
      "match_shape": 0.996,
      "target": 161
    }
  ]
}
